pypeliner/__init__.py
pypeliner/exceptions.py
pypeliner/runner_configuration.py
pypeliner/processors/__init__.py
pypeliner/processors/base.py
pypeliner/readers/__init__.py
pypeliner/readers/base.py
pypeliner/readers/bulk_readers/__init__.py
pypeliner/readers/bulk_readers/file_readers.py
pypeliner/readers/bulk_readers/image_readers.py
pypeliner/readers/stream_readers/__init__.py
pypeliner/readers/stream_readers/file_readers.py
pypeliner/readers/stream_readers/image_readers.py
pypeliner/runners/__init__.py
pypeliner/runners/base.py
pypeliner/utils/__init__.py
pypeliner/utils/csv_utils.py
pypeliner/utils/decorators.py
pypeliner/utils/string_utils.py
simple_pypeliner-1.3.dist-info/LICENSE
simple_pypeliner-1.3.dist-info/METADATA
simple_pypeliner-1.3.dist-info/WHEEL
simple_pypeliner-1.3.dist-info/top_level.txt
simple_pypeliner-1.3.dist-info/RECORD
