Metadata-Version: 2.1
Name: simple-pypeliner
Version: 1.3
Summary: A simple python framework for building data processing pipelines
Author-email: Fareck Allony <fareck.allony.mail@gmail.com>
Project-URL: Homepage, https://github.com/allonios/pypeliner
Project-URL: Documentation, https://simple-pypeliner.readthedocs.io/en/latest/
Project-URL: Bug Tracker, https://github.com/allonios/pypeliner/issues
Classifier: Programming Language :: Python :: 3
Classifier: License :: OSI Approved :: MIT License
Classifier: Operating System :: OS Independent
Requires-Python: >=3.7
License-File: LICENSE
